gather_vision/__init__.py
gather_vision/app.py
gather_vision/cli.py
gather_vision/model.py
gather_vision/plugin.py
gather_vision/utils.py
gather_vision-0.0.3.dist-info/LICENSE
gather_vision-0.0.3.dist-info/METADATA
gather_vision-0.0.3.dist-info/WHEEL
gather_vision-0.0.3.dist-info/entry_points.txt
gather_vision-0.0.3.dist-info/top_level.txt
gather_vision-0.0.3.dist-info/RECORD
